{"name":"Educe","tagline":"Abstract representation of a discourse-annotated corpus.","body":"[![Build Status](https://secure.travis-ci.org/kowey/educe.png)](http://travis-ci.org/kowey/educe)\r\n\r\n## About\r\n\r\nEduce is a library for working with discourse-annotated corpora.\r\nIt also includes some utility scripts for building, maintaining,\r\nand for querying these corpora. Currently supported corpora are\r\n\r\n* (SDRT) [STAC][stac] corpus\r\n* (RST) RST Discourse Treebank (experimental, 2014-07-14)\r\n* (PDTB) Penn Discourse Treebank (experimental, 2014-07-14)\r\n\r\nIf you have a discourse-annotated corpus, or are trying to build one,\r\nyou may find it useful to add support for it to educe.\r\n\r\n## Documentation\r\n\r\n* [API documentation][api-docs]\r\n\r\n## Installation\r\n\r\nFirst, try\r\n\r\n    pip --help\r\n\r\nIf this doesn't work, download this [setup script][setup-distribute] and\r\nrun\r\n\r\n    python distribute_setup.py\r\n    easy_install pip\r\n\r\nIf you have pip installed, then install educe and its dependencies:\r\n\r\n    pip install -r requirements.txt .\r\n\r\n\r\n## See also\r\n\r\n* [Attelo][attelo]: a discourse parser\r\n\r\n[attelo]: http://github.com/kowey/attelo\r\n[setup-distribute]: http://python-distribute.org/distribute_setup.py\r\n[stac]:  http://www.irit.fr/STAC/\r\n[glozz]: http://www.glozz.org/\r\n[api-docs]:  https://educe.readthedocs.org/en/latest/api-doc/educe.html\r\n","google":"","note":"Don't delete this file! It's used internally to help with page regeneration."}